pyctlmbatchtoolbox/__init__.py
pyctlmbatchtoolbox/command.py
pyctlmbatchtoolbox/command_condition.py
pyctlmbatchtoolbox/command_connectionprofiles.py
pyctlmbatchtoolbox/command_deploy.py
pyctlmbatchtoolbox/command_hostgroup.py
pyctlmbatchtoolbox/command_logs.py
pyctlmbatchtoolbox/command_order.py
pyctlmbatchtoolbox/command_status.py
pyctlmbatchtoolbox/command_token.py
pyctlmbatchtoolbox/common.py
pyctlmbatchtoolbox/context.py
pyctlmbatchtoolbox-0.0.4.dist-info/LICENSE
pyctlmbatchtoolbox-0.0.4.dist-info/METADATA
pyctlmbatchtoolbox-0.0.4.dist-info/WHEEL
pyctlmbatchtoolbox-0.0.4.dist-info/entry_points.txt
pyctlmbatchtoolbox-0.0.4.dist-info/top_level.txt
pyctlmbatchtoolbox-0.0.4.dist-info/RECORD
