Metadata-Version: 2.1
Name: pyctlmbatchtoolbox
Version: 0.0.4
Summary: Set of command line tools used to interact with Control-M.
Home-page: https://github.com/AmadeusITGroup/pyctlmbatchtoolbox
Author: Jose Morales Aragon
Author-email: jmoralesaragon@users.noreply.github.com
License: UNKNOWN
Project-URL: Homepage, https://github.com/AmadeusITGroup/pyctlmbatchtoolbox
Keywords: bmc controlm batch
Platform: UNKNOWN
Classifier: Programming Language :: Python :: 3
Classifier: License :: OSI Approved :: BSD License
Classifier: Operating System :: OS Independent
Requires-Python: >=3.6
License-File: LICENSE
Requires-Dist: requests
Requires-Dist: urllib3
